lokidb_sdk/__init__.py
lokidb_sdk/gen_grpc/__init__.py
lokidb_sdk/gen_grpc/spec.proto
lokidb_sdk/gen_grpc/spec_pb2.py
lokidb_sdk/gen_grpc/spec_pb2_grpc.py
lokidb_sdk/grpc_client.py
lokidb_sdk-0.1.0.dist-info/WHEEL
lokidb_sdk-0.1.0.dist-info/METADATA
lokidb_sdk-0.1.0.dist-info/RECORD
