Metadata-Version: 2.1
Name: lokidb-sdk
Version: 0.1.0
Summary: LokiDB python client SDK
Author: yehoyada
Author-email: hvuhsg5@gmail.com
Requires-Python: >=3.8,<4.0
Classifier: Programming Language :: Python :: 3
Classifier: Programming Language :: Python :: 3.8
Classifier: Programming Language :: Python :: 3.9
Classifier: Programming Language :: Python :: 3.10
Requires-Dist: grpcio (>=1.48.1,<2.0.0)
Requires-Dist: requests (>=2.28.1,<3.0.0)
